oracollector/__init__.py
oracollector/__main__.py
oracollector/config_oracle.yaml
pgcollector/.DS_Store
pgcollector/__init__.py
pgcollector/__main__.py
pgcollector/config.yaml
compare/__init__.py
compare/__main__.py
importer/__init__.py
importer/__main__.py
importer/create_pg_user.sql
importer/extracts/.gitignore
reporter/.DS_Store
reporter/.gitignore
reporter/__init__.py
reporter/__main__.py
reporter/css/jquery-3.7.0.js
reporter/css/jquery.dataTables.min.css
reporter/css/jquery.dataTables.min.js
reporter/queries/column_type_mismatch.sql
reporter/queries/instances.sql
reporter/queries/line_count_mismatch.sql
reporter/queries/line_count_mismatch_detailed.sql
reporter/queries/missing_columns.sql
reporter/queries/missing_indexes.sql
reporter/queries/missing_objects.sql
reporter/queries/missing_plsql.sql
reporter/queries/missing_role_grants.sql
reporter/queries/missing_sys_privs.sql
reporter/queries/object_counts.sql
reporter/queries/object_counts_mismatch.sql
reporter/queries/object_counts_per_schema.sql
reporter/queries/object_counts_per_schema_mismatch.sql
reporter/queries_schema_mapped/instances.sql
reporter/queries_schema_mapped/missing_columns.sql
reporter/queries_schema_mapped/missing_objects.sql
reporter/queries_schema_mapped/missing_plsql.sql
reporter/queries_schema_mapped/object_counts.sql
reporter/query_config.yaml
reporter/query_config_schema_mapped.yaml
reporter/report.css
db_compare-0.2.1.dist-info/LICENSE
db_compare-0.2.1.dist-info/METADATA
db_compare-0.2.1.dist-info/WHEEL
db_compare-0.2.1.dist-info/entry_points.txt
db_compare-0.2.1.dist-info/RECORD
