Metadata-Version: 2.1
Name: db_compare
Version: 0.2.1
Summary: Tool to compare database schema and objects
License: Google
Author: sametkaradag
Author-email: sametkaradag@gmail.com
Requires-Python: >=3.9,<4.0
Classifier: License :: Other/Proprietary License
Classifier: Programming Language :: Python :: 3
Classifier: Programming Language :: Python :: 3.9
Classifier: Programming Language :: Python :: 3.10
Classifier: Programming Language :: Python :: 3.11
Classifier: Programming Language :: Python :: 3.12
Requires-Dist: google-cloud (==0.34.0)
Requires-Dist: google-cloud-bigquery (>=3.25.0,<4.0.0)
Requires-Dist: google-cloud-secret-manager (>=2.21.1,<3.0.0)
Requires-Dist: oracledb (>=2.3.0,<3.0.0)
Requires-Dist: pandas (>=2.2.2,<3.0.0)
Requires-Dist: psycopg2-binary (>=2.9.10,<3.0.0)
Requires-Dist: pyyaml (==6.0.1)
Requires-Dist: sqlalchemy (>=2.0.32,<3.0.0)
Requires-Dist: tabulate (>=0.9.0,<0.10.0)
